[
    {
        "isTemplate": false,
        "count": 0,
        "updated": null,
        "data": [
            {
                "text": "blue",
                "userDefined": true,
                "alias": "monsterAttribute1",
                "meta": "@monsterAttribute1"
            },
            {
                "text": " ",
                "userDefined": false
            },
            {
                "text": "red",
                "userDefined": true,
                "alias": "monsterAttribute2",
                "meta": "@monsterAttribute2"
            },
            {
                "text": " ",
                "userDefined": false
            },
            {
                "text": "cards",
                "userDefined": true,
                "alias": "targetObject",
                "meta": "@targetObject"
            },
            {
                "text": " ",
                "userDefined": false
            },
            {
                "text": "from",
                "userDefined": false
            },
            {
                "text": " ",
                "userDefined": false
            },
            {
                "text": "beach",
                "userDefined": true,
                "alias": "monsterSeries",
                "meta": "@monsterSeries"
            }
        ]
    },
    {
        "isTemplate": false,
        "count": 0,
        "updated": null,
        "data": [
            {
                "text": "water",
                "userDefined": true,
                "alias": "monsterAttribute1",
                "meta": "@monsterAttribute1"
            },
            {
                "text": "/",
                "userDefined": false
            },
            {
                "text": "green",
                "userDefined": true,
                "alias": "monsterAttribute2",
                "meta": "@monsterAttribute2"
            },
            {
                "text": " ",
                "userDefined": false
            },
            {
                "text": "cards",
                "userDefined": true,
                "alias": "targetObject",
                "meta": "@targetObject"
            },
            {
                "text": " ",
                "userDefined": false
            },
            {
                "text": "from",
                "userDefined": false
            },
            {
                "text": " ",
                "userDefined": false
            },
            {
                "text": "yugioh",
                "userDefined": true,
                "alias": "monsterSeries",
                "meta": "@monsterSeries"
            }
        ]
    },
    {
        "isTemplate": false,
        "count": 0,
        "updated": null,
        "data": [
            {
                "text": "monsters",
                "userDefined": true,
                "alias": "targetObject",
                "meta": "@targetObject"
            },
            {
                "text": " ",
                "userDefined": false
            },
            {
                "text": "from",
                "userDefined": false
            },
            {
                "text": " ",
                "userDefined": false
            },
            {
                "text": "monster hunter",
                "userDefined": true,
                "alias": "monsterSeries",
                "meta": "@monsterSeries"
            }
        ]
    }
]